qaviton_handlers/__init__.py
qaviton_handlers/catch.py
qaviton_handlers/try_context.py
qaviton_handlers/try_decorator.py
qaviton_handlers/try_functions.py
qaviton_handlers/utils/__init__.py
qaviton_handlers/utils/error.py
qaviton_handlers/utils/handle_failed_attempt.py
qaviton_handlers/utils/log.py
qaviton_handlers-2019.10.18.12.58.53.756274.dist-info/LICENSE
qaviton_handlers-2019.10.18.12.58.53.756274.dist-info/METADATA
qaviton_handlers-2019.10.18.12.58.53.756274.dist-info/WHEEL
qaviton_handlers-2019.10.18.12.58.53.756274.dist-info/top_level.txt
qaviton_handlers-2019.10.18.12.58.53.756274.dist-info/RECORD
