Metadata-Version: 2.1
Name: qaviton-handlers
Version: 2019.10.18.12.58.53.756274
Summary: qaviton handlers
Home-page: https://github.com/qaviton/qaviton_handlers
Author: yehonadav
Author-email: yonadav.barilan@gmail.com
License: apache-2.0
Platform: UNKNOWN
Classifier: Programming Language :: Python :: 3.6
